portscan.py
portscan-1.1.dist-info/LICENSE
portscan-1.1.dist-info/METADATA
portscan-1.1.dist-info/WHEEL
portscan-1.1.dist-info/entry_points.txt
portscan-1.1.dist-info/top_level.txt
portscan-1.1.dist-info/RECORD
